{
  "credit": "Made with Blockbench",
  "parent": "minecraft:block/stairs",
  "textures": {
    "5": "babylonmod:block/lime_gypsum_plaster_top_dark",
    "particle": "babylonmod:block/lime_gypsum_plaster_top_dark"
  },
  "elements": [
    {
      "from": [8, 0, 0],
      "to": [16, 12, 16],
      "faces": {
        "north": { "uv": [0.5, 0.5, 7, 11.5], "texture": "#5" },
        "east": { "uv": [0, 4, 16, 16], "texture": "#5" },
        "south": { "uv": [0, 0, 8, 12.5], "texture": "#5" },
        "west": { "uv": [0, 0, 16, 12], "texture": "#5" },
        "up": { "uv": [1, 8, 16, 16], "rotation": 270, "texture": "#5" },
        "down": { "uv": [1, 8, 16, 16], "rotation": 270, "texture": "#5" }
      }
    }
  ]
}
